azure/mgmt/commerce/__init__.py
azure/mgmt/commerce/usage_management_client.py
azure/mgmt/commerce/version.py
azure/mgmt/commerce/models/__init__.py
azure/mgmt/commerce/models/error_response.py
azure/mgmt/commerce/models/info_field.py
azure/mgmt/commerce/models/meter_info.py
azure/mgmt/commerce/models/monetary_commitment.py
azure/mgmt/commerce/models/monetary_credit.py
azure/mgmt/commerce/models/offer_term_info.py
azure/mgmt/commerce/models/rate_card_query_parameters.py
azure/mgmt/commerce/models/recurring_charge.py
azure/mgmt/commerce/models/resource_rate_card_info.py
azure/mgmt/commerce/models/usage_aggregation.py
azure/mgmt/commerce/models/usage_aggregation_paged.py
azure/mgmt/commerce/models/usage_management_client_enums.py
azure/mgmt/commerce/operations/__init__.py
azure/mgmt/commerce/operations/rate_card_operations.py
azure/mgmt/commerce/operations/usage_aggregates_operations.py
azure_mgmt_commerce-1.0.1.dist-info/DESCRIPTION.rst
azure_mgmt_commerce-1.0.1.dist-info/METADATA
azure_mgmt_commerce-1.0.1.dist-info/RECORD
azure_mgmt_commerce-1.0.1.dist-info/WHEEL
azure_mgmt_commerce-1.0.1.dist-info/metadata.json
azure_mgmt_commerce-1.0.1.dist-info/top_level.txt
